<?xml version="1.0" encoding="UTF-8"?>
<ncic-ex:Exchange xmlns:ncic="http://cjis.fbi.gov/ncic/NIEM"
    xmlns:xsi="http://www.w3.org/2001/XMLSchema-instance"
    xmlns:nc="http://release.niem.gov/niem/niem-core/3.0/"
    xmlns:j="http://release.niem.gov/niem/domains/jxdm/5.2/"
    xmlns:s="http://release.niem.gov/niem/structures/3.0/"
    xmlns:ncic-ex="http://cjis.fbi.gov/ncic/NIEM/Exchange"
    xsi:schemaLocation="http://cjis.fbi.gov/ncic/NIEM/Exchange ../../xsd/NCICExchange.xsd">
    
    <!-- ******************************************************************************** -->
    <!-- ncic-ex:Message. -->
    <!-- ******************************************************************************** -->
    <ncic-ex:Message>
        <!-- MKE - Message Key -->
        <ncic:MessageTransactionText>$.8.</ncic:MessageTransactionText>
        <ncic-ex:NotificationRecordData s:ref="NotificationRecordData"/>
    </ncic-ex:Message>
    
    <!-- ******************************************************************************** -->
    <!-- ncic-ex:NotificationRecordData. -->
    <!-- ******************************************************************************** -->
    <ncic-ex:NotificationRecordData s:id="NotificationRecordData">
        <nc:CaveatText>
            OUT OF STATE AT <!--<hhmm>--> EST <!--<yyyymmdd>-->
            SEE IDENTIFIER(S) LIC/<!--<LIC>-->1GH890 VIN/<!--<VIN>-->WDBBA48D1GA051451
            NIC/<!--<NIC>-->V0123456789 OCA/<!--<OCA>-->WVV990167 OAN/<!--<OAN>-->THE MERRY MERZ
        </nc:CaveatText>
        <ncic:VehicleRecord s:ref="VehicleInfo"/>
        <!--<Input-Transaction>-->
        <ncic-ex:IncomingMessage />
    </ncic-ex:NotificationRecordData>
    
    <!-- ******************************************************************************** -->
    <!-- ncic:VehicleRecord. -->
    <!-- ******************************************************************************** -->
    <ncic:VehicleRecord s:id="VehicleInfo">
        <nc:Incident s:ref="VehicleIncidentDataSection"/>
        <j:ItemNCICIdentification>
            <!-- NIC - NCIC number -->
            <nc:IdentificationID>V0123456789</nc:IdentificationID>
        </j:ItemNCICIdentification>
        <j:ConveyanceRegistrationAssociation>
            <j:ItemRegistration s:ref="VehicleRegistrationDataSection"/>
            <nc:Item s:ref="VehicleInfoDataSection"/>
        </j:ConveyanceRegistrationAssociation>
    </ncic:VehicleRecord>
    
    <!-- ******************************************************************************** -->
    <!-- nc:Incident. -->
    <!-- ******************************************************************************** -->
    <nc:Incident s:id="VehicleIncidentDataSection">
        <j:ActivityAugmentation>
            <!-- OCA - Originating Agency Case Number -->
            <j:CaseNumberText>WVV990167</j:CaseNumberText>
        </j:ActivityAugmentation>
    </nc:Incident>
    
    <!-- ******************************************************************************** -->
    <!-- nc:Vehicle. -->
    <!-- ******************************************************************************** -->
    <nc:Vehicle s:id="VehicleInfoDataSection">
        <!-- OAN - Owner applied number -->
        <nc:ItemOwnerAppliedID>THE MERRY MERZ</nc:ItemOwnerAppliedID>
        <nc:VehicleIdentification>
            <!-- VIN - Vehicle identification number -->
            <nc:IdentificationID>WDBBA48D1GA051451</nc:IdentificationID>
        </nc:VehicleIdentification>
        <!-- VMA - Vehicle make -->
        <ncic:VehicleMakeCodeText>AERO</ncic:VehicleMakeCodeText>
    </nc:Vehicle>
    
    <!-- ******************************************************************************** -->
    <!-- j:ConveyanceRegistration. -->
    <!-- ******************************************************************************** -->
    <j:ConveyanceRegistration s:id="VehicleRegistrationDataSection">
        <j:ConveyanceRegistrationPlateIdentification>
            <!-- LIC - License plate number -->
            <nc:IdentificationID>1GH890</nc:IdentificationID>
        </j:ConveyanceRegistrationPlateIdentification>
    </j:ConveyanceRegistration>
</ncic-ex:Exchange>
