<?xml version="1.0" encoding="UTF-8"?>
<w:WantList w:release="4.0" w:product="NIEM" w:nillableDefault="true"
  xmlns:j="http://release.niem.gov/niem/domains/jxdm/6.0/"
  xmlns:w="http://niem.gov/niem/wantlist/2.2" xmlns:nc="http://release.niem.gov/niem/niem-core/4.0/">
  <w:Element w:name="j:OrganizationAugmentation" w:isReference="false" w:nillable="true"/>
  <w:Element w:name="nc:Address" w:isReference="false" w:nillable="false"/>
  <w:Element w:name="nc:ContactMailingAddress" w:isReference="false" w:nillable="false"/>
  <w:Element w:name="nc:Date" w:isReference="false" w:nillable="false"/>
  <w:Element w:name="nc:JurisdictionText" w:isReference="false" w:nillable="false"/>
  <w:Element w:name="nc:LocationCountryName" w:isReference="false" w:nillable="false"/>
  <w:Element w:name="nc:LocationStateName" w:isReference="false" w:nillable="false"/>
  <w:Element w:name="nc:LocationStreet" w:isReference="false" w:nillable="false"/>
  <w:Element w:name="nc:OrganizationCategoryText" w:isReference="false" w:nillable="false"/>
  <w:Element w:name="nc:StatusText" w:isReference="false" w:nillable="false"/>
  <w:Type w:name="j:OrganizationAugmentationType" w:isRequested="false">
    <w:ElementInType w:name="j:OrganizationJurisdiction"
      w:isReference="false" w:minOccurs="0" w:maxOccurs="unbounded"/>
  </w:Type>
  <w:Type w:name="nc:AddressType" w:isRequested="false">
    <w:ElementInType w:name="nc:AddressDeliveryPointAbstract"
      w:isReference="false" w:minOccurs="0" w:maxOccurs="unbounded"/>
    <w:ElementInType w:name="nc:LocationCityName" w:isReference="false"
      w:minOccurs="0" w:maxOccurs="unbounded"/>
    <w:ElementInType w:name="nc:LocationState" w:isReference="false"
      w:minOccurs="0" w:maxOccurs="unbounded"/>
    <w:ElementInType w:name="nc:LocationCountry" w:isReference="false"
      w:minOccurs="0" w:maxOccurs="unbounded"/>
    <w:ElementInType w:name="nc:LocationPostalCode"
      w:isReference="false" w:minOccurs="0" w:maxOccurs="unbounded"/>
  </w:Type>
  <w:Type w:name="nc:ContactInformationType" w:isRequested="false">
    <w:ElementInType w:name="nc:ContactMeansAbstract"
      w:isReference="false" w:minOccurs="0" w:maxOccurs="unbounded"/>
  </w:Type>
  <w:Type w:name="nc:CountryType" w:isRequested="false">
    <w:ElementInType w:name="nc:CountryRepresentation"
      w:isReference="false" w:minOccurs="0" w:maxOccurs="unbounded"/>
  </w:Type>
  <w:Type w:name="nc:DateType" w:isRequested="false">
    <w:ElementInType w:name="nc:DateRepresentation"
      w:isReference="false" w:minOccurs="0" w:maxOccurs="unbounded"/>
  </w:Type>
  <w:Type w:name="nc:IdentificationType" w:isRequested="false">
    <w:ElementInType w:name="nc:IdentificationID" w:isReference="false"
      w:minOccurs="0" w:maxOccurs="unbounded"/>
    <w:ElementInType w:name="nc:IdentificationCategoryAbstract"
      w:isReference="false" w:minOccurs="0" w:maxOccurs="unbounded"/>
    <w:ElementInType w:name="nc:IdentificationSourceText"
      w:isReference="false" w:minOccurs="0" w:maxOccurs="unbounded"/>
  </w:Type>
  <w:Type w:name="nc:JurisdictionType" w:isRequested="false">
    <w:ElementInType w:name="nc:JurisdictionAbstract"
      w:isReference="false" w:minOccurs="0" w:maxOccurs="unbounded"/>
  </w:Type>
  <w:Type w:name="nc:LocationType" w:isRequested="false">
    <w:ElementInType w:name="nc:LocationAddressAbstract"
      w:isReference="false" w:minOccurs="0" w:maxOccurs="unbounded"/>
  </w:Type>
  <w:Type w:name="nc:OrganizationType" w:isRequested="true">
    <w:ElementInType w:name="nc:OrganizationCategoryAbstract"
      w:isReference="false" w:minOccurs="0" w:maxOccurs="unbounded"/>
    <w:ElementInType w:name="nc:OrganizationDoingBusinessAsName"
      w:isReference="false" w:minOccurs="0" w:maxOccurs="unbounded"/>
    <w:ElementInType w:name="nc:OrganizationIdentification"
      w:isReference="false" w:minOccurs="0" w:maxOccurs="unbounded"/>
    <w:ElementInType w:name="nc:OrganizationLocation"
      w:isReference="false" w:minOccurs="0" w:maxOccurs="unbounded"/>
    <w:ElementInType w:name="nc:OrganizationName" w:isReference="false"
      w:minOccurs="0" w:maxOccurs="unbounded"/>
    <w:ElementInType w:name="nc:OrganizationOtherIdentification"
      w:isReference="false" w:minOccurs="0" w:maxOccurs="unbounded"/>
    <w:ElementInType w:name="nc:OrganizationPrimaryContactInformation"
      w:isReference="false" w:minOccurs="0" w:maxOccurs="unbounded"/>
    <w:ElementInType w:name="nc:OrganizationStatus"
      w:isReference="false" w:minOccurs="0" w:maxOccurs="unbounded"/>
    <w:ElementInType w:name="nc:OrganizationAugmentationPoint"
      w:isReference="false" w:minOccurs="0" w:maxOccurs="unbounded"/>
  </w:Type>
  <w:Type w:name="nc:StateType" w:isRequested="false">
    <w:ElementInType w:name="nc:StateRepresentation"
      w:isReference="false" w:minOccurs="0" w:maxOccurs="unbounded"/>
  </w:Type>
  <w:Type w:name="nc:StatusType" w:isRequested="false">
    <w:ElementInType w:name="nc:StatusAbstract" w:isReference="false"
      w:minOccurs="0" w:maxOccurs="unbounded"/>
    <w:ElementInType w:name="nc:StatusDate" w:isReference="false"
      w:minOccurs="0" w:maxOccurs="unbounded"/>
  </w:Type>
  <w:Type w:name="nc:StreetType" w:isRequested="false">
    <w:ElementInType w:name="nc:StreetFullText" w:isReference="false"
      w:minOccurs="0" w:maxOccurs="unbounded"/>
  </w:Type>
</w:WantList>
